tests/__init__.py
tests/test_simple.py
Short_Py-1.3.1.dist-info/LICENSE.txt
Short_Py-1.3.1.dist-info/METADATA
Short_Py-1.3.1.dist-info/WHEEL
Short_Py-1.3.1.dist-info/top_level.txt
Short_Py-1.3.1.dist-info/RECORD
