Metadata-Version: 2.1
Name: Short-Py
Version: 1.3.1
Summary: A module that will make your coding easier
Home-page: https://github.com/Ethan7080/Py-Simplify
Author: Ethan Wang
Author-email: Ethan Wang <ethanwanglife@gmail.com>
Maintainer-email: Daniel Fong <dfong8818@gmail.com>
License: MIT License
Project-URL: Homepage, https://github.com/Ethan7080/Short-Py
Project-URL: Bug Reports, https://github.com/Ethan7080/Short-Py/issues
Project-URL: Source, https://github.com/Ethan7080/Short-Py
Keywords: easy,help,module
Classifier: Development Status :: 4 - Beta
Classifier: Intended Audience :: Developers
Classifier: Topic :: Software Development :: Build Tools
Classifier: License :: OSI Approved :: MIT License
Classifier: Programming Language :: Python :: 3
Classifier: Programming Language :: Python :: 3.8
Classifier: Programming Language :: Python :: 3.9
Classifier: Programming Language :: Python :: 3.10
Classifier: Programming Language :: Python :: 3.11
Classifier: Programming Language :: Python :: 3.12
Classifier: Programming Language :: Python :: 3 :: Only
Requires-Python: >=3.6
License-File: LICENSE.txt
Provides-Extra: dev
Requires-Dist: check-manifest ; extra == 'dev'
Provides-Extra: test
Requires-Dist: coverage ; extra == 'test'
